canvasutils/__init__.py
canvasutils/submit.py
canvasutils/utils.py
canvasutils-0.4.1.dist-info/LICENSE
canvasutils-0.4.1.dist-info/WHEEL
canvasutils-0.4.1.dist-info/METADATA
canvasutils-0.4.1.dist-info/RECORD
