Metadata-Version: 2.1
Name: canvasutils
Version: 0.4.1
Summary: Utilities for interacting with Canvas using Python and the canvasapi.
Home-page: https://github.com/TomasBeuzen/canvasutils
Author: Tomas Beuzen
Author-email: tomas.beuzen@stat.ubc.ca
Requires-Python: >=3.7,<4.0
Classifier: Programming Language :: Python :: 3
Classifier: Programming Language :: Python :: 3.7
Classifier: Programming Language :: Python :: 3.8
Requires-Dist: canvasapi (>=2.0.0,<3.0.0)
Requires-Dist: ipywidgets (>=7.5.1,<8.0.0)
Project-URL: Repository, https://github.com/TomasBeuzen/canvasutils
